speculative_decoding_metrics/__init__.py
speculative_decoding_metrics/evaluator.py
speculative_decoding_metrics/main.py
speculative_decoding_metrics/plotter.py
speculative_decoding_metrics-0.1.6.dist-info/licenses/LICENSE
speculative_decoding_metrics-0.1.6.dist-info/METADATA
speculative_decoding_metrics-0.1.6.dist-info/WHEEL
speculative_decoding_metrics-0.1.6.dist-info/top_level.txt
speculative_decoding_metrics-0.1.6.dist-info/RECORD
