Metadata-Version: 2.4
Name: speculative_decoding_metrics
Version: 0.1.6
Summary: A package that evaluates and plots results to test Throughput based on number of draft tokens
Author-email: Mitul Garg <mitulgarg3@gmail.com>
License: MIT License
Project-URL: Homepage, https://github.com/mitulgarg/Speculative-Decoding-DraftToken-Analysis
Requires-Python: >=3.8
License-File: LICENSE
Requires-Dist: sentence-transformers==3.3.1
Requires-Dist: huggingface-hub==0.30.1
Requires-Dist: rouge-score==0.1.2
Requires-Dist: matplotlib==3.10.1
Requires-Dist: numpy==2.2.4
Requires-Dist: transformers==4.48.0
Requires-Dist: mlx-lm==0.22.3
Requires-Dist: torch==2.6.0
Requires-Dist: scikit-learn==1.6.1
Dynamic: license-file
